easytax/__init__.py
easytax/base/FlatTax.py
easytax/base/FlatTaxBracket.py
easytax/base/ProgressiveTax.py
easytax/base/ProgressiveTaxBracket.py
easytax/base/RegressiveTax.py
easytax/base/RegressiveTaxBracket.py
easytax/base/Tax.py
easytax/base/__init__.py
easytax/brackets/FederalIncomeTaxBrackets.py
easytax/brackets/FederalLongTermCapitalGainsTaxBrackets.py
easytax/brackets/GeorgiaStateIncomeTaxBrackets.py
easytax/brackets/GeorgiaStateLongTermCapitalGainsTaxBrackets.py
easytax/brackets/MedicareIncomeTaxBrackets.py
easytax/brackets/NetInvestmentIncomeTaxBrackets.py
easytax/brackets/SocialSecurityIncomeTaxBrackets.py
easytax/brackets/__init__.py
easytax/deductions/FederalStandardDeductions.py
easytax/deductions/__init__.py
easytax/handler/FederalTaxHandler.py
easytax/handler/IndividualIncomeTaxHandlerBase.py
easytax/handler/MedicareTaxHandler.py
easytax/handler/NetInvestmentIncomeTaxHandler.py
easytax/handler/RegionalTaxHandlerBase.py
easytax/handler/SocialSecurityTaxHandler.py
easytax/handler/StateWithoutTaxHandler.py
easytax/handler/TaxHandler.py
easytax/handler/__init__.py
easytax/handler/states/GeorgiaTaxHandler.py
easytax/income/FederalIncomeHandler.py
easytax/income/PayrollTaxIncomeHandler.py
easytax/utils/Constants.py
easytax/utils/InputValidator.py
easytax/utils/Logger.py
easytax/utils/__init__.py
easytax-0.0.20.dist-info/METADATA
easytax-0.0.20.dist-info/WHEEL
easytax-0.0.20.dist-info/licenses/LICENSE
easytax-0.0.20.dist-info/RECORD
